cartoon_diffusion/__init__.py
cartoon_diffusion/pipeline.py
cartoon_diffusion-0.1.0.dist-info/licenses/LICENSE
cartoon_diffusion-0.1.0.dist-info/METADATA
cartoon_diffusion-0.1.0.dist-info/WHEEL
cartoon_diffusion-0.1.0.dist-info/top_level.txt
cartoon_diffusion-0.1.0.dist-info/RECORD
