Metadata-Version: 2.4
Name: cartoon-diffusion
Version: 0.1.0
Summary: AI-powered image to cartoon conversion using diffusion models
Home-page: https://github.com/wizcodes12/cartoon-diffusion
Author: wizcodes12
Author-email: 
Keywords: ai,machine learning,diffusion,cartoon,image processing
Classifier: Development Status :: 3 - Alpha
Classifier: Intended Audience :: Developers
Classifier: License :: OSI Approved :: MIT License
Classifier: Operating System :: OS Independent
Classifier: Programming Language :: Python :: 3
Classifier: Programming Language :: Python :: 3.8
Classifier: Programming Language :: Python :: 3.9
Classifier: Programming Language :: Python :: 3.10
Classifier: Programming Language :: Python :: 3.11
Classifier: Topic :: Scientific/Engineering :: Artificial Intelligence
Classifier: Topic :: Multimedia :: Graphics :: Graphics Conversion
Requires-Python: >=3.8
License-File: LICENSE
Requires-Dist: torch>=1.9.0
Requires-Dist: torchvision>=0.10.0
Requires-Dist: diffusers>=0.20.0
Requires-Dist: transformers>=4.20.0
Requires-Dist: huggingface-hub>=0.15.0
Requires-Dist: Pillow>=8.0.0
Requires-Dist: numpy>=1.21.0
Requires-Dist: opencv-python>=4.5.0
Requires-Dist: mediapipe>=0.10.0
Dynamic: author
Dynamic: classifier
Dynamic: description
Dynamic: description-content-type
Dynamic: home-page
Dynamic: keywords
Dynamic: license-file
Dynamic: requires-dist
Dynamic: requires-python
Dynamic: summary
